odoo/addons/mrp_stock_rule_propagate_bom_line/README.rst
odoo/addons/mrp_stock_rule_propagate_bom_line/__init__.py
odoo/addons/mrp_stock_rule_propagate_bom_line/__manifest__.py
odoo/addons/mrp_stock_rule_propagate_bom_line/i18n/it.po
odoo/addons/mrp_stock_rule_propagate_bom_line/i18n/mrp_stock_rule_propagate_bom_line.pot
odoo/addons/mrp_stock_rule_propagate_bom_line/models/__init__.py
odoo/addons/mrp_stock_rule_propagate_bom_line/models/stock_move.py
odoo/addons/mrp_stock_rule_propagate_bom_line/models/stock_rule.py
odoo/addons/mrp_stock_rule_propagate_bom_line/readme/CONTRIBUTORS.rst
odoo/addons/mrp_stock_rule_propagate_bom_line/readme/DESCRIPTION.rst
odoo/addons/mrp_stock_rule_propagate_bom_line/readme/ROADMAP.rst
odoo/addons/mrp_stock_rule_propagate_bom_line/static/description/icon.png
odoo/addons/mrp_stock_rule_propagate_bom_line/static/description/index.html
odoo/addons/mrp_stock_rule_propagate_bom_line/tests/__init__.py
odoo/addons/mrp_stock_rule_propagate_bom_line/tests/test_stock_rule_group_kit_line.py
odoo/addons/mrp_stock_rule_propagate_bom_line/views/stock_rule.xml
odoo14_addon_mrp_stock_rule_propagate_bom_line-14.0.1.0.1.dev3.dist-info/METADATA
odoo14_addon_mrp_stock_rule_propagate_bom_line-14.0.1.0.1.dev3.dist-info/WHEEL
odoo14_addon_mrp_stock_rule_propagate_bom_line-14.0.1.0.1.dev3.dist-info/top_level.txt
odoo14_addon_mrp_stock_rule_propagate_bom_line-14.0.1.0.1.dev3.dist-info/RECORD
